odoo10_addon_stock_move_common_dest-10.0.1.1.1-py3.8-nspkg.pth
odoo/addons/stock_move_common_dest/README.rst
odoo/addons/stock_move_common_dest/__init__.py
odoo/addons/stock_move_common_dest/__manifest__.py
odoo/addons/stock_move_common_dest/i18n/stock_move_common_dest.pot
odoo/addons/stock_move_common_dest/models/__init__.py
odoo/addons/stock_move_common_dest/models/stock_move.py
odoo/addons/stock_move_common_dest/readme/CONTRIBUTORS.rst
odoo/addons/stock_move_common_dest/readme/DESCRIPTION.rst
odoo/addons/stock_move_common_dest/static/description/icon.png
odoo/addons/stock_move_common_dest/static/description/index.html
odoo/addons/stock_move_common_dest/tests/__init__.py
odoo/addons/stock_move_common_dest/tests/test_move_common_dest.py
odoo/addons/stock_move_common_dest/views/stock_move.xml
odoo10_addon_stock_move_common_dest-10.0.1.1.1.dist-info/METADATA
odoo10_addon_stock_move_common_dest-10.0.1.1.1.dist-info/WHEEL
odoo10_addon_stock_move_common_dest-10.0.1.1.1.dist-info/namespace_packages.txt
odoo10_addon_stock_move_common_dest-10.0.1.1.1.dist-info/top_level.txt
odoo10_addon_stock_move_common_dest-10.0.1.1.1.dist-info/RECORD
